{
  "generatedAt": "2025-10-11T18:09:05.334Z",
  "documentsIndexed": 318,
  "tokensIndexed": 215798,
  "truncatedDocuments": 1,
  "buildTimeMs": 207162.071,
  "indexFileBytes": 54023687,
  "indexFile": "result\\index\\inverted-index.json",
  "chunkSizeStats": [
    {
      "chunkSize": 160,
      "vocabularySize": 27425,
      "totalChunks": 1534,
      "totalTokens": 215798
    },
    {
      "chunkSize": 240,
      "vocabularySize": 27425,
      "totalChunks": 1074,
      "totalTokens": 215798
    }
  ],
  "memoryUsage": {
    "rss": 1119420416,
    "heapTotal": 468176896,
    "heapUsed": 377196664,
    "external": 33242103
  },
  "indexingConfig": {
    "chunkSizes": [
      160,
      240
    ],
    "primaryChunkSize": 160,
    "minTokenLength": 3,
    "maxTokensPerDocument": 25000
  }
}